py_pgtest/__init__.py
py_pgtest/cli.py
py_pgtest/pgtap_prefix.sql
py_pgtest/pgtest.py
py_pgtest-0.1.12.dist-info/METADATA
py_pgtest-0.1.12.dist-info/RECORD
py_pgtest-0.1.12.dist-info/WHEEL
py_pgtest-0.1.12.dist-info/entry_points.txt
py_pgtest-0.1.12.dist-info/top_level.txt
