Metadata-Version: 2.1
Name: py-pgtest
Version: 0.1.12
Summary: testing pg made easy
Home-page: https://github.com/zh217/py-pgtest
Author: Ziyang Hu
Author-email: hu.ziyang@cantab.net
License: MIT
Platform: UNKNOWN
Requires-Dist: pytest-tap
Requires-Dist: watchdog
Requires-Dist: colorama
